calculadora/coolstuff.py
calculadora/main.py
calculadora/areas/IrrAreas.py
calculadora/areas/areas.py
calculadora/areas/areas2D.py
calculadora/areas/areas3D.py
calculadora/areas/test_irr_polygon.py
calculadora/arithmetic/arithmetic.py
calculadora/graphics/graph.py
calculadora/special-functions/special-functions.py
calculadora/trigonometry/trig.py
juan_calc-0.1.0.dist-info/licenses/LICENSE
juan_calc-0.1.0.dist-info/METADATA
juan_calc-0.1.0.dist-info/WHEEL
juan_calc-0.1.0.dist-info/top_level.txt
juan_calc-0.1.0.dist-info/RECORD
