Metadata-Version: 2.4
Name: Juan_Calc
Version: 0.1.0
Summary: La mejor calculadora nunca antes vista
Author-email: Juan Esteban Neira Díaz <jueneirad@udistrital.edu.co>
Project-URL: homepage, https://github.com/configurarpc/calculadora
Classifier: Programming Language :: Python :: 3
Classifier: License :: OSI Approved :: MIT License
Classifier: Operating System :: OS Independent
Requires-Python: >=3.8
License-File: LICENSE
Requires-Dist: tensorflow
Dynamic: license-file
